android_xml_translater/__dist_version__.py
android_xml_translater/__init__.py
android_xml_translater/__main__.py
android_xml_translater/__version__.py
android_xml_translater/arguments_helper.py
android_xml_translater/axt.py
android_xml_translater/translated_strings.xml
android_xml_translater-1.0.3.dist-info/LICENSE
android_xml_translater-1.0.3.dist-info/METADATA
android_xml_translater-1.0.3.dist-info/WHEEL
android_xml_translater-1.0.3.dist-info/entry_points.txt
android_xml_translater-1.0.3.dist-info/top_level.txt
android_xml_translater-1.0.3.dist-info/RECORD
