Metadata-Version: 2.1
Name: android-xml-translater
Version: 1.0.3
Summary: Script to translate Android strings.xml
Author: Harkame
Project-URL: repository, https://github.com/Harkame/android-xml-translater
Classifier: Programming Language :: Python
Requires-Python: >=3.8
License-File: LICENSE
Requires-Dist: deep-translator >=1.11.4
Requires-Dist: beautifulsoup4 >=4.12.2
Requires-Dist: lxml >=4.9.3
Provides-Extra: dev
Requires-Dist: pytest >=7 ; extra == 'dev'
Requires-Dist: pytest-cov >=4.1.0 ; extra == 'dev'
